{"type":"Topology","transform":{"scale":[0.000032151585158515844,0.00001483769376937693],"translate":[-4.3932006,55.7812767]},"objects":{"CommArea":{"type":"GeometryCollection","geometries":[{"type":"Polygon","arcs":[[0]],"id":"Eastern Necropolis (Janesfield)","properties":{"osm_id":29435498}},{"type":"Polygon","arcs":[[1]],"properties":{"osm_id":134585848}},{"type":"Polygon","arcs":[[2]],"properties":{"osm_id":134585849}},{"type":"Polygon","arcs":[[3,4,5,6]],"properties":{"osm_id":134585893}},{"type":"Polygon","arcs":[[7]],"properties":{"osm_id":134585901}},{"type":"Polygon","arcs":[[8,9]],"id":"Athletes' Village","properties":{"osm_id":156831890}},{"type":"Polygon","arcs":[[10]],"id":"Belvidere Village","properties":{"osm_id":156831891}},{"type":"Polygon","arcs":[[11]],"properties":{"osm_id":158371801}},{"type":"Polygon","arcs":[[12,13,-6,14]],"properties":{"osm_id":158545440}},{"type":"Polygon","arcs":[[15]],"properties":{"osm_id":158545441}},{"type":"Polygon","arcs":[[16,17,18,19]],"properties":{"osm_id":158545442}},{"type":"Polygon","arcs":[[20]],"properties":{"osm_id":158545443}},{"type":"Polygon","arcs":[[21]],"properties":{"osm_id":162222965}},{"type":"Polygon","arcs":[[22,-17]],"id":"Dalmarnock Waste Water Treatment Works","properties":{"osm_id":166272154}},{"type":"Polygon","arcs":[[-4,23,-9,24]],"properties":{"osm_id":166272155}},{"type":"Polygon","arcs":[[25,26,27,28]],"id":"Cemex Rutherglen Plan","properties":{"osm_id":167854467}},{"type":"MultiPolygon","arcs":[[[-28,29]],[[30,-26]]],"properties":{"osm_id":167854516}},{"type":"Polygon","arcs":[[31,32]],"properties":{"osm_id":167854519}},{"type":"Polygon","arcs":[[33,-32]],"properties":{"osm_id":167854524}},{"type":"Polygon","arcs":[[34]],"properties":{"osm_id":167854525}},{"type":"Polygon","arcs":[[35]],"properties":{"osm_id":167881455}},{"type":"Polygon","arcs":[[36]],"properties":{"osm_id":167881457}},{"type":"Polygon","arcs":[[37]],"properties":{"osm_id":167881458}},{"type":"Polygon","arcs":[[38]],"properties":{"osm_id":167881459}},{"type":"Polygon","arcs":[[39]],"properties":{"osm_id":167881461}},{"type":"Polygon","arcs":[[40]],"properties":{"osm_id":167881466}},{"type":"Polygon","arcs":[[41]],"properties":{"osm_id":167881469}},{"type":"Polygon","arcs":[[42]],"properties":{"osm_id":169744188}},{"type":"Polygon","arcs":[[43,44]],"id":"Westthorn","properties":{"osm_id":179689713}},{"type":"Polygon","arcs":[[45,-44]],"id":"Westthorn Allotments","properties":{"osm_id":179689715}},{"type":"Polygon","arcs":[[46]],"properties":{"osm_id":199576200}},{"type":"Polygon","arcs":[[47]],"properties":{"osm_id":199576201}},{"type":"Polygon","arcs":[[48]],"properties":{"osm_id":199576203}},{"type":"Polygon","arcs":[[49]],"properties":{"osm_id":199576527}},{"type":"Polygon","arcs":[[50,-19]],"properties":{"osm_id":203112950}},{"type":"Polygon","arcs":[[51]],"properties":{"osm_id":205664355}},{"type":"Polygon","arcs":[[52]],"properties":{"osm_id":205664356}},{"type":"Polygon","arcs":[[-13,53,54]],"properties":{"osm_id":211929778}},{"type":"Polygon","arcs":[[55,56]],"properties":{"osm_id":223034494}},{"type":"Polygon","arcs":[[-57,57]],"properties":{"osm_id":223034495}}]},"Village":{"type":"GeometryCollection","geometries":[{"type":"Polygon","arcs":[[8,9]],"id":"Athletes' Village","properties":{"osm_id":156831890}}]},"Celtic":{"type":"GeometryCollection","crs":{"type":"name","properties":{"name":"urn:ogc:def:crs:OGC:1.3:CRS84"}},"geometries":[{"type":"Polygon","arcs":[[58]],"id":"Celtic Park","properties":{"osm_id":-904494}}]},"Velodrome":{"type":"GeometryCollection","geometries":[{"type":"Polygon","arcs":[[-60]],"id":"Sir Chris Hoy Velodrome","properties":{"osm_id":156831896}}]},"Ibrox":{"type":"GeometryCollection","crs":{"type":"name","properties":{"name":"urn:ogc:def:crs:OGC:1.3:CRS84"}},"geometries":[{"type":"Polygon","arcs":[[60]],"id":"Ibrox Stadium","properties":{"osm_id":15090854}}]},"city":{"type":"GeometryCollection","crs":{"type":"name","properties":{"name":"urn:ogc:def:crs:OGC:1.3:CRS84"}},"geometries":[{"type":"Polygon","arcs":[[61,62,63,64,65]],"id":"Glasgow City","properties":{"osm_id":-1906767}}]},"riverClyde":{"type":"GeometryCollection","geometries":[{"type":"MultiLineString","arcs":[[66],[67],[68],[69],[70],[71],[72],[73],[74],[75],[76],[77]],"id":"River Clyde","properties":{"osm_id":39216698}},{"type":"MultiLineString","arcs":[[78],[79],[80],[81],[82],[83],[84],[85],[86],[87],[88],[89]],"id":"River Clyde","properties":{"osm_id":44634816}},{"type":"LineString","arcs":[90],"id":"River Clyde","properties":{"osm_id":44634817}},{"type":"MultiLineString","arcs":[[91],[92],[93],[94],[95],[96],[97],[98],[99],[100],[101],[102],[103],[104],[105],[106],[107],[108],[109],[110],[111,112]],"id":"River Clyde","properties":{"osm_id":51105085}},{"type":"MultiLineString","arcs":[[113],[114]],"id":"River Clyde","properties":{"osm_id":153245244}}]},"IbroxArea":{"type":"GeometryCollection","geometries":[{"type":"Polygon","arcs":[[115]],"properties":{"osm_id":23106226}},{"type":"Polygon","arcs":[[116]],"properties":{"osm_id":28126506}},{"type":"Polygon","arcs":[[117]],"properties":{"osm_id":105478402}},{"type":"Polygon","arcs":[[118]],"properties":{"osm_id":105926771}},{"type":"Polygon","arcs":[[119,120,121,122]],"properties":{"osm_id":117203007}},{"type":"Polygon","arcs":[[123]],"properties":{"osm_id":132882618}},{"type":"Polygon","arcs":[[124]],"properties":{"osm_id":132882637}},{"type":"Polygon","arcs":[[125]],"properties":{"osm_id":132957987}},{"type":"Polygon","arcs":[[126]],"properties":{"osm_id":133171235}},{"type":"Polygon","arcs":[[127]],"properties":{"osm_id":133386708}},{"type":"Polygon","arcs":[[128]],"properties":{"osm_id":133386852}},{"type":"Polygon","arcs":[[129]],"properties":{"osm_id":133390985}},{"type":"Polygon","arcs":[[130]],"properties":{"osm_id":133390986}},{"type":"Polygon","arcs":[[131]],"properties":{"osm_id":133403193}},{"type":"Polygon","arcs":[[132]],"properties":{"osm_id":133405051}},{"type":"Polygon","arcs":[[133]],"properties":{"osm_id":133476060}},{"type":"Polygon","arcs":[[134]],"properties":{"osm_id":133476079}},{"type":"Polygon","arcs":[[135]],"properties":{"osm_id":133881002}},{"type":"Polygon","arcs":[[136]],"properties":{"osm_id":133882077}},{"type":"MultiPolygon","arcs":[[[137]],[[138]]],"properties":{"osm_id":133882078}},{"type":"MultiPolygon","arcs":[[[139]],[[140]]],"properties":{"osm_id":133885390}},{"type":"Polygon","arcs":[[141]],"properties":{"osm_id":133898154}},{"type":"Polygon","arcs":[[142]],"properties":{"osm_id":148325566}},{"type":"Polygon","arcs":[[143]],"properties":{"osm_id":219354838}},{"type":"Polygon","arcs":[[144,-120]],"properties":{"osm_id":228048072}}]},"CommTransit":{"type":"GeometryCollection","geometries":[{"type":"Point","coordinates":[5516,4672],"id":"Gallowgate, Fielden Street/ Fielden Place","properties":{"osm_id":432455386}},{"type":"Point","coordinates":[5408,4566],"id":"Barrowfield, London Road/ Fordneuk Street","properties":{"osm_id":432455417}},{"type":"Point","coordinates":[5425,4574],"id":"Barrowfield, London Road/ Fordneuk Street","properties":{"osm_id":432455419}},{"type":"Point","coordinates":[5213,4560],"id":"Glasgow, London Road / Bridgeton Station","properties":{"osm_id":432455421}},{"type":"Point","coordinates":[5813,4499],"id":"Parkhead, London Road/ Kinnear Road","properties":{"osm_id":1705790364}},{"type":"Point","coordinates":[5625,4539],"id":"Barrowfield, London Road/ Boden Street","properties":{"osm_id":2089782361}},{"type":"Point","coordinates":[5320,4582],"id":"Barrowfield, London Road/ Brook Street","properties":{"osm_id":2089782362}},{"type":"Point","coordinates":[5752,4518],"id":"Barrowfield, London Road/ Davaar Street","properties":{"osm_id":2089782363}},{"type":"Point","coordinates":[5547,4542],"id":"Barrowfield, London Road/ Fielden Street","properties":{"osm_id":2089782364}},{"type":"Point","coordinates":[5667,4524],"id":"Barrowfield, London Road/ Nuneaton Street","properties":{"osm_id":2089782365}},{"type":"Point","coordinates":[5545,4552],"id":"Barrowfield, London Road/ Stamford Street","properties":{"osm_id":2089782366}},{"type":"Point","coordinates":[6119,4363],"id":"Parkhead, London Road/ Canmore street","properties":{"osm_id":2089782378}},{"type":"Point","coordinates":[5874,4498],"id":"Parkhead, London Road/ Dalriada Street","properties":{"osm_id":2089782379}},{"type":"Point","coordinates":[6070,4396],"id":"Parkhead, London Road/ Macbeth Street","properties":{"osm_id":2089782381}},{"type":"Point","coordinates":[5246,4491],"id":"Bridgeton, Dalmarnock Road/ Megan Street","properties":{"osm_id":2089788412}},{"type":"Point","coordinates":[5221,4502],"id":"Bridgeton, Dalmarnock Road/ Megan Street","properties":{"osm_id":2089788419}},{"type":"Point","coordinates":[5336,4366],"id":"Bridgeton, Dalmarnock Road/ Queen Mary Street","properties":{"osm_id":2089788427}},{"type":"Point","coordinates":[5312,4390],"id":"Bridgeton, Dalmarnock Road/ Queen Mary Street","properties":{"osm_id":2089788438}},{"type":"Point","coordinates":[5360,4217],"id":"Bridgeton, Dunn Street/ Old Dalmarnock Road","properties":{"osm_id":2089788445}},{"type":"Point","coordinates":[5371,4241],"id":"Bridgeton, Dunn Street/ Old Dalmarnock Road","properties":{"osm_id":2089788453}},{"type":"Point","coordinates":[5212,4245],"id":"Bridgeton, Franklin Street/ Main Street","properties":{"osm_id":2089788460}},{"type":"Point","coordinates":[5181,4224],"id":"Bridgeton, Main Street/","properties":{"osm_id":2089788494}},{"type":"Point","coordinates":[5174,4238],"id":"Bridgeton, Main Street/","properties":{"osm_id":2089788495}},{"type":"Point","coordinates":[5189,4547],"id":"Bridgeton, Main Street/ Bridgeton Cross","properties":{"osm_id":2089788496}},{"type":"Point","coordinates":[5187,4562],"id":"Bridgeton, Main Street/ Bridgeton Cross","properties":{"osm_id":2089788497}},{"type":"Point","coordinates":[5176,4374],"id":"Bridgeton, Main Street/ Tullis Street","properties":{"osm_id":2089788498}},{"type":"Point","coordinates":[5182,4388],"id":"Bridgeton, Main Street/ Tullis Street","properties":{"osm_id":2089788499}},{"type":"Point","coordinates":[5198,4181],"id":"Bridgeton, Rumford Street/ Main Street","properties":{"osm_id":2089788500}},{"type":"Point","coordinates":[5420,4227],"id":"Dalmarnock, Dalmarnock Road/ Bartholomew Street","properties":{"osm_id":2089788505}},{"type":"Point","coordinates":[5429,4199],"id":"Dalmarnock, Dalmarnock Road/ Bartholowmew Street","properties":{"osm_id":2089788506}},{"type":"Point","coordinates":[5522,4658],"id":"Gallowgate, Fielden Street/ Fielden Place","properties":{"osm_id":2089788507}},{"type":"Point","coordinates":[5657,3885],"id":"Dalmarnock, Dalmarnock Road/ Birkwood Street","properties":{"osm_id":2089866737}},{"type":"Point","coordinates":[5672,3878],"id":"Dalmarnock, Dalmarnock Road/ Birkwood street","properties":{"osm_id":2089866748}},{"type":"Point","coordinates":[5594,3975],"id":"Dalmarnock, Dalmarnock Road/ Davidson Street","properties":{"osm_id":2089866772}},{"type":"Point","coordinates":[5553,4006],"id":"Dalmarnock, Dalmarnock Road/ Davidson Street","properties":{"osm_id":2089866785}},{"type":"Point","coordinates":[5515,4064],"id":"Dalmarnock, Dalmarnock Road/ Springfield Road","properties":{"osm_id":2089866791}},{"type":"Point","coordinates":[5471,4119],"id":"Dalmarnock, Dalmarnock Road/ Swanston Street","properties":{"osm_id":2089866797}},{"type":"Point","coordinates":[5556,4043],"id":"Dalmarnock, Springfield Road/ Baltic Street","properties":{"osm_id":2089866804}},{"type":"Point","coordinates":[5567,4055],"id":"Dalmarnock, Springfield Road/ Dalmarnock Road","properties":{"osm_id":2089866811}},{"type":"Point","coordinates":[5722,4212],"id":"Dalmarnock, Springfield Road/ Irvine street","properties":{"osm_id":2089866818}},{"type":"Point","coordinates":[5733,4237],"id":"Dalmarnock, Springfield Road/ Irvine street","properties":{"osm_id":2089866827}},{"type":"Point","coordinates":[5668,4122],"id":"Dalmarnock, Springfield Road/ Sorn Street","properties":{"osm_id":2089866832}},{"type":"Point","coordinates":[5659,4124],"id":"Dalmarnock, Springfield Road/ Sorn street","properties":{"osm_id":2089866839}},{"type":"Point","coordinates":[6041,4583],"id":"Parkhead, Dechmont Street/ Springfield Road","properties":{"osm_id":2089866853}},{"type":"Point","coordinates":[6062,4516],"id":"Parkhead, Helenvale Street/ Glamis Road","properties":{"osm_id":2089866889}},{"type":"Point","coordinates":[6073,4528],"id":"Parkhead, Helenvale Street/ Glamis Road","properties":{"osm_id":2089866896}},{"type":"Point","coordinates":[6124,4637],"id":"Parkhead, Helenvale Street/ Helenvale Sports Are","properties":{"osm_id":2089866900}},{"type":"Point","coordinates":[6002,4584],"id":"Parkhead, Springfield Road/ Dechmont Street","properties":{"osm_id":2089866904}},{"type":"Point","coordinates":[5847,4376],"id":"Parkhead, Springfield Road/ Gailes Street","properties":{"osm_id":2089866910}},{"type":"Point","coordinates":[5862,4381],"id":"Parkhead, Springfield Road/ Gailes Street","properties":{"osm_id":2089866924}},{"type":"Point","coordinates":[6057,4700],"id":"Parkhead, Springfield Road/ Gallowgate","properties":{"osm_id":2089866931}},{"type":"Point","coordinates":[5969,4512],"id":"Parkhead, Springfield Road/ Janefield Street","properties":{"osm_id":2089866935}},{"type":"Point","coordinates":[5915,4460],"id":"Parkhead, Springfield Road/ London Road","properties":{"osm_id":2089866938}},{"type":"Point","coordinates":[6170,4651],"id":"Parkhead, Tollcross Road/ Sorby Street","properties":{"osm_id":2089872802}},{"type":"Point","coordinates":[6160,4669],"id":"Parkhead, Tollcross Road/ Sorby street","properties":{"osm_id":2089872809}}]},"IbroxTransit":{"type":"GeometryCollection","geometries":[{"type":"Point","coordinates":[5516,4672],"id":"Gallowgate, Fielden Street/ Fielden Place","properties":{"osm_id":432455386}},{"type":"Point","coordinates":[5408,4566],"id":"Barrowfield, London Road/ Fordneuk Street","properties":{"osm_id":432455417}},{"type":"Point","coordinates":[5425,4574],"id":"Barrowfield, London Road/ Fordneuk Street","properties":{"osm_id":432455419}},{"type":"Point","coordinates":[5213,4560],"id":"Glasgow, London Road / Bridgeton Station","properties":{"osm_id":432455421}},{"type":"Point","coordinates":[5813,4499],"id":"Parkhead, London Road/ Kinnear Road","properties":{"osm_id":1705790364}},{"type":"Point","coordinates":[5625,4539],"id":"Barrowfield, London Road/ Boden Street","properties":{"osm_id":2089782361}},{"type":"Point","coordinates":[5320,4582],"id":"Barrowfield, London Road/ Brook Street","properties":{"osm_id":2089782362}},{"type":"Point","coordinates":[5752,4518],"id":"Barrowfield, London Road/ Davaar Street","properties":{"osm_id":2089782363}},{"type":"Point","coordinates":[5547,4542],"id":"Barrowfield, London Road/ Fielden Street","properties":{"osm_id":2089782364}},{"type":"Point","coordinates":[5667,4524],"id":"Barrowfield, London Road/ Nuneaton Street","properties":{"osm_id":2089782365}},{"type":"Point","coordinates":[5545,4552],"id":"Barrowfield, London Road/ Stamford Street","properties":{"osm_id":2089782366}},{"type":"Point","coordinates":[6119,4363],"id":"Parkhead, London Road/ Canmore street","properties":{"osm_id":2089782378}},{"type":"Point","coordinates":[5874,4498],"id":"Parkhead, London Road/ Dalriada Street","properties":{"osm_id":2089782379}},{"type":"Point","coordinates":[6070,4396],"id":"Parkhead, London Road/ Macbeth Street","properties":{"osm_id":2089782381}},{"type":"Point","coordinates":[5246,4491],"id":"Bridgeton, Dalmarnock Road/ Megan Street","properties":{"osm_id":2089788412}},{"type":"Point","coordinates":[5221,4502],"id":"Bridgeton, Dalmarnock Road/ Megan Street","properties":{"osm_id":2089788419}},{"type":"Point","coordinates":[5336,4366],"id":"Bridgeton, Dalmarnock Road/ Queen Mary Street","properties":{"osm_id":2089788427}},{"type":"Point","coordinates":[5312,4390],"id":"Bridgeton, Dalmarnock Road/ Queen Mary Street","properties":{"osm_id":2089788438}},{"type":"Point","coordinates":[5360,4217],"id":"Bridgeton, Dunn Street/ Old Dalmarnock Road","properties":{"osm_id":2089788445}},{"type":"Point","coordinates":[5371,4241],"id":"Bridgeton, Dunn Street/ Old Dalmarnock Road","properties":{"osm_id":2089788453}},{"type":"Point","coordinates":[5212,4245],"id":"Bridgeton, Franklin Street/ Main Street","properties":{"osm_id":2089788460}},{"type":"Point","coordinates":[5181,4224],"id":"Bridgeton, Main Street/","properties":{"osm_id":2089788494}},{"type":"Point","coordinates":[5174,4238],"id":"Bridgeton, Main Street/","properties":{"osm_id":2089788495}},{"type":"Point","coordinates":[5189,4547],"id":"Bridgeton, Main Street/ Bridgeton Cross","properties":{"osm_id":2089788496}},{"type":"Point","coordinates":[5187,4562],"id":"Bridgeton, Main Street/ Bridgeton Cross","properties":{"osm_id":2089788497}},{"type":"Point","coordinates":[5176,4374],"id":"Bridgeton, Main Street/ Tullis Street","properties":{"osm_id":2089788498}},{"type":"Point","coordinates":[5182,4388],"id":"Bridgeton, Main Street/ Tullis Street","properties":{"osm_id":2089788499}},{"type":"Point","coordinates":[5198,4181],"id":"Bridgeton, Rumford Street/ Main Street","properties":{"osm_id":2089788500}},{"type":"Point","coordinates":[5420,4227],"id":"Dalmarnock, Dalmarnock Road/ Bartholomew Street","properties":{"osm_id":2089788505}},{"type":"Point","coordinates":[5429,4199],"id":"Dalmarnock, Dalmarnock Road/ Bartholowmew Street","properties":{"osm_id":2089788506}},{"type":"Point","coordinates":[5522,4658],"id":"Gallowgate, Fielden Street/ Fielden Place","properties":{"osm_id":2089788507}},{"type":"Point","coordinates":[5657,3885],"id":"Dalmarnock, Dalmarnock Road/ Birkwood Street","properties":{"osm_id":2089866737}},{"type":"Point","coordinates":[5672,3878],"id":"Dalmarnock, Dalmarnock Road/ Birkwood street","properties":{"osm_id":2089866748}},{"type":"Point","coordinates":[5594,3975],"id":"Dalmarnock, Dalmarnock Road/ Davidson Street","properties":{"osm_id":2089866772}},{"type":"Point","coordinates":[5553,4006],"id":"Dalmarnock, Dalmarnock Road/ Davidson Street","properties":{"osm_id":2089866785}},{"type":"Point","coordinates":[5515,4064],"id":"Dalmarnock, Dalmarnock Road/ Springfield Road","properties":{"osm_id":2089866791}},{"type":"Point","coordinates":[5471,4119],"id":"Dalmarnock, Dalmarnock Road/ Swanston Street","properties":{"osm_id":2089866797}},{"type":"Point","coordinates":[5556,4043],"id":"Dalmarnock, Springfield Road/ Baltic Street","properties":{"osm_id":2089866804}},{"type":"Point","coordinates":[5567,4055],"id":"Dalmarnock, Springfield Road/ Dalmarnock Road","properties":{"osm_id":2089866811}},{"type":"Point","coordinates":[5722,4212],"id":"Dalmarnock, Springfield Road/ Irvine street","properties":{"osm_id":2089866818}},{"type":"Point","coordinates":[5733,4237],"id":"Dalmarnock, Springfield Road/ Irvine street","properties":{"osm_id":2089866827}},{"type":"Point","coordinates":[5668,4122],"id":"Dalmarnock, Springfield Road/ Sorn Street","properties":{"osm_id":2089866832}},{"type":"Point","coordinates":[5659,4124],"id":"Dalmarnock, Springfield Road/ Sorn street","properties":{"osm_id":2089866839}},{"type":"Point","coordinates":[6041,4583],"id":"Parkhead, Dechmont Street/ Springfield Road","properties":{"osm_id":2089866853}},{"type":"Point","coordinates":[6062,4516],"id":"Parkhead, Helenvale Street/ Glamis Road","properties":{"osm_id":2089866889}},{"type":"Point","coordinates":[6073,4528],"id":"Parkhead, Helenvale Street/ Glamis Road","properties":{"osm_id":2089866896}},{"type":"Point","coordinates":[6124,4637],"id":"Parkhead, Helenvale Street/ Helenvale Sports Are","properties":{"osm_id":2089866900}},{"type":"Point","coordinates":[6002,4584],"id":"Parkhead, Springfield Road/ Dechmont Street","properties":{"osm_id":2089866904}},{"type":"Point","coordinates":[5847,4376],"id":"Parkhead, Springfield Road/ Gailes Street","properties":{"osm_id":2089866910}},{"type":"Point","coordinates":[5862,4381],"id":"Parkhead, Springfield Road/ Gailes Street","properties":{"osm_id":2089866924}},{"type":"Point","coordinates":[6057,4700],"id":"Parkhead, Springfield Road/ Gallowgate","properties":{"osm_id":2089866931}},{"type":"Point","coordinates":[5969,4512],"id":"Parkhead, Springfield Road/ Janefield Street","properties":{"osm_id":2089866935}},{"type":"Point","coordinates":[5915,4460],"id":"Parkhead, Springfield Road/ London Road","properties":{"osm_id":2089866938}},{"type":"Point","coordinates":[6170,4651],"id":"Parkhead, Tollcross Road/ Sorby Street","properties":{"osm_id":2089872802}},{"type":"Point","coordinates":[6160,4669],"id":"Parkhead, Tollcross Road/ Sorby street","properties":{"osm_id":2089872809}}]}},"arcs":[[[5961,4719],[-20,-69],[-24,-63],[-5,5],[-16,21],[-84,91],[5,15],[144,0]],[[5948,4435],[3,8],[29,35],[-28,12],[-72,9],[16,3],[17,3],[46,13],[26,4],[39,6],[42,-1],[-8,-20],[5,-3],[48,-1],[0,-20],[-4,-19],[-18,-24],[12,-14],[-10,-15],[30,-27],[54,61],[32,-41],[-10,-5],[3,-7],[7,-17],[-53,-45],[-14,16],[9,8],[-24,28],[-10,-11],[-77,72],[-27,21],[-41,-50],[-22,21]],[[6208,4594],[-19,13],[15,30],[-66,47],[-56,-117],[40,-10],[-2,-25],[-40,-1],[1,31],[-89,-12],[-11,29],[20,42],[18,-13],[22,48],[-25,20],[21,43],[171,0],[0,-125]],[[5661,4065],[-58,-24],[-5,-13],[9,-20],[38,19],[18,-35],[10,5],[25,-48],[-15,-11],[20,-43],[5,-11]],[[5708,3884],[-10,-8],[21,-46],[0,-14],[-14,0],[-5,17],[-47,74],[-38,47],[-79,77],[4,6],[57,23],[-19,69],[24,11],[-43,52],[-15,-16]],[[5544,4176],[-9,16]],[[5535,4192],[47,54],[17,-20],[20,30],[52,18],[18,9],[39,47],[41,-48],[-100,-124],[-15,-43],[-11,-24],[6,-9],[12,-17]],[[5529,4709],[1,10],[176,0],[6,-4],[-14,-25],[-4,-41],[-29,5],[-13,8],[-10,-1],[-6,-69],[63,-11],[-4,-51],[-107,18],[-77,12],[4,50],[42,-6],[6,59],[-41,7],[7,39]],[[5801,4215],[-38,45]],[[5763,4260],[158,195],[69,-65],[-86,-112],[-14,4],[-57,-8],[-20,-26],[-12,-33]],[[6030,4429],[94,-90],[-43,-69],[-41,40],[-8,-12],[-50,47],[-20,-28],[-7,8],[75,104]],[[5202,4577],[0,2],[1,1],[2,0],[29,-1],[10,1],[16,10],[5,-13],[-1,-6],[-18,-5],[-13,0],[-15,3],[-16,8]],[[5492,4445],[6,48]],[[5498,4493],[62,-13],[5,-1],[6,58],[116,-16],[-6,-73],[-11,-36],[-18,-36],[-133,-158],[6,-10],[10,-16]],[[5544,4176],[29,-50],[-22,-14],[-52,-22],[-28,39],[-12,0],[-15,5],[-34,9],[-36,2],[-1,-78],[-35,0],[-117,6],[0,50],[12,5],[15,1],[78,-1],[1,42],[30,37],[44,51],[83,88],[8,99]],[[5196,4066],[45,-1],[-8,-94],[-59,65],[22,30]],[[5479,3832],[-35,0],[-1,-16]],[[5443,3816],[-104,0],[-2,37],[-3,32],[-66,70],[-4,-4],[-30,19],[4,56],[45,-7],[83,-12],[-3,-25],[64,-22],[29,128],[7,-1],[4,-123],[42,-12],[30,48],[56,-58],[-10,-15],[36,-53],[-17,-19],[-34,43],[-5,-5]],[[5565,3893],[-6,-6],[-26,-15],[-19,-5],[1,-33],[2,-18]],[[5517,3816],[-13,0],[-18,61],[-10,-1],[3,-44]],[[5157,4128],[15,0],[1,-58],[-9,-17],[-7,7],[0,68]],[[5519,4617],[-3,4],[8,39],[4,3],[33,-7],[-5,-45],[-37,6]],[[5479,3832],[4,-16],[-40,0]],[[5661,4065],[-5,27],[19,51],[19,34],[69,83]],[[5801,4215],[-11,-48],[0,-56],[38,-77],[14,-9],[43,-25],[18,-43],[2,-54],[-36,-54],[-55,-30],[-25,-1],[-42,82],[-30,-22],[-9,6]],[[5233,3845],[3,-29]],[[5236,3816],[-29,0]],[[5207,3816],[6,26]],[[5213,3842],[20,3]],[[5207,3816],[-24,0],[-3,20],[33,6]],[[5233,3845],[28,5],[3,-27],[-1,-7],[-27,0]],[[5201,3848],[-5,38]],[[5196,3886],[-2,19],[31,5],[54,-39],[5,-12],[4,1],[6,-16],[0,-28],[-24,0],[1,7],[-5,34],[-65,-9]],[[5201,3848],[-37,-6],[-4,38],[36,6]],[[5157,3833],[17,2],[2,-19],[-19,0],[0,17]],[[5294,4288],[0,10],[6,7],[0,3],[-2,4],[0,15],[7,3],[11,-22],[0,-14],[-11,-11],[-11,5]],[[5443,4487],[13,-1],[-4,-33],[-12,2],[3,32]],[[5386,4354],[5,-6],[-11,-19],[-7,13],[13,12]],[[5413,4536],[19,-3],[-2,-22],[-19,3],[2,22]],[[5445,4531],[14,-2],[-3,-24],[-13,3],[2,23]],[[5406,4494],[26,-4],[-1,-10],[-25,4],[0,10]],[[5180,4181],[60,-1],[0,-28],[-26,-4],[-14,-13],[-20,3],[0,43]],[[5471,4719],[-20,-12],[-4,0],[-6,-5],[-6,17],[36,0]],[[6120,4019],[19,19]],[[6139,4038],[44,44],[25,32],[0,-298],[-20,0],[1,4],[0,35],[-5,29],[-36,63],[-41,56],[13,16]],[[6120,4019],[-96,122],[5,9],[12,6],[9,6],[89,-124]],[[6096,4409],[60,71],[2,1],[2,0],[15,-18],[1,-3],[-1,-5],[-56,-66],[-12,13],[-6,2],[-5,5]],[[6189,4461],[14,18],[4,1],[1,-2],[0,-47],[-20,23],[0,4],[1,3]],[[6164,4492],[3,0],[24,-6],[5,-2],[0,-4],[-11,-15],[-4,-1],[-19,21],[-1,4],[3,3]],[[6208,4489],[-48,13],[-46,6],[-40,1],[-4,2],[-1,3],[5,11],[20,-1],[39,-5],[39,-9],[36,-10],[0,-11]],[[5565,3893],[40,-49],[21,24],[9,-7],[17,25],[30,-42],[12,-28],[-177,0]],[[5793,4338],[55,69],[11,-14],[-56,-68],[-10,13]],[[5819,4495],[0,-4],[-17,-20],[-27,32],[44,-8]],[[5492,4445],[-96,16],[-19,-14],[40,-62],[58,-10],[-6,-15],[-8,1],[-11,-17],[-3,-9],[-27,-29],[-16,-14],[-4,5],[-16,-15],[-1,3],[-7,-4],[12,-21],[-9,-7],[-35,30],[-16,24],[-6,5],[-13,21],[0,18],[-8,24],[-9,-3],[-6,-2],[-2,6],[-1,7],[-14,-4],[-22,1],[-1,-76],[27,0],[0,-15],[6,-1],[15,0]],[[5294,4288],[14,-13],[1,-44],[-2,0],[0,-23],[-8,0],[1,-10],[-26,0],[-1,-51],[-25,0],[-27,1],[-20,-16],[-33,7],[-11,1],[0,548],[3,11],[2,13],[13,-1],[5,8],[15,0],[0,-77],[-11,-29],[-6,-19],[-17,-14],[14,-47],[11,10],[4,17],[15,-15],[-10,-18],[42,-38],[30,-24],[7,5],[-14,36],[-9,15],[-1,5],[-12,11],[-4,8],[3,4],[8,0],[47,8],[-1,10],[23,6],[14,1],[3,-3],[0,-5],[38,-7],[-4,-37],[44,-6],[4,37],[91,-10],[-6,-50]],[[5936,4632],[27,87],[42,0],[-2,-8],[-14,6],[-3,-11],[3,-6],[-1,-5],[-17,-52],[-13,-25]],[[5958,4618],[-22,14]],[[5958,4618],[9,21],[4,2],[17,-11],[-12,-28],[11,-6],[-10,-23],[11,-7],[-17,-29],[-36,37],[-17,12],[18,46]],[[5783,4619],[1,4],[0,4],[2,4],[2,3],[-4,5],[26,35],[5,5],[6,3],[4,2],[3,0],[5,-1],[4,-1],[5,-3],[4,-3],[42,-48],[7,-7],[3,-6],[2,-7],[1,-7],[-1,-3],[-1,-6],[-2,-7],[-1,-1],[-28,-38],[-7,6],[-7,-5],[-6,-2],[-3,0],[-4,1],[-5,4],[-8,8],[-5,-1],[-1,2],[-4,0],[-4,3],[0,4],[-3,-1],[-1,2],[-1,0],[-5,5],[0,2],[-2,2],[0,3],[-2,0],[-4,3],[0,5],[-1,2],[1,2],[-2,1],[1,2],[1,1],[-6,6],[-3,5],[-2,4],[-2,5],[0,4]],[[5737,4460],[-4,-6],[-1,-6],[1,-7],[4,-5],[3,-5],[7,-8],[4,-4],[3,0],[3,-1],[4,1],[3,1],[26,32],[1,2],[1,6],[-1,7],[-3,5],[-9,13],[-4,3],[-5,2],[-6,-1],[-4,-2],[-23,-27]],[[2549,4819],[1,15],[4,2],[15,61],[23,15],[9,3],[55,-22],[3,-2],[4,-4],[2,-4],[4,-8],[1,-5],[0,-7],[-13,-59],[-8,-23],[-18,7],[-82,31]],[[8744,3153],[7,-18],[38,-65],[5,-16],[1,-17],[-3,-10],[-4,-11],[-9,-8],[-7,-3],[-9,0],[-33,4],[-17,9],[-16,12],[-11,15],[-16,16],[-34,25],[-25,23],[-13,16],[-12,9],[-17,17],[-20,17],[-20,26],[-17,16],[-20,13],[-49,29],[-30,31],[-27,35],[-25,28],[-39,29],[-41,38],[-14,18],[-2,12],[-12,12],[-46,37],[-12,8],[-13,4],[-15,1],[-12,-4],[-25,-16],[-38,-19],[-24,-16],[-39,-35],[-45,-45],[-12,-9],[-21,-13],[-45,-16],[-51,-27],[-27,-20],[-52,-54],[-36,-32],[-32,-25],[-25,-12],[-11,-3],[-12,-1],[-29,4],[-31,8],[-51,-3],[-31,-6],[-103,-11],[-20,-7],[-40,-3],[-14,-6],[-41,-8],[-46,-20],[-25,-13],[-11,-9],[-33,-21]],[[7185,3063],[-44,-31],[-22,-17],[-16,-18],[-74,-52],[-33,-26],[-40,-52],[-53,-38],[-25,-15],[-9,-3],[-5,-1],[-26,4],[-18,7],[-21,14],[-24,33],[-15,33],[-10,37],[-8,63],[-18,78],[-14,77],[-14,48],[-12,24],[-8,30],[-3,19],[-6,19],[-4,38],[-1,155],[-7,80],[-5,32],[-4,12],[-8,19],[-12,19],[-11,11],[-13,10],[-140,62],[-23,8],[-16,0]],[[6423,3742],[-19,-5],[-33,-25],[-68,-69],[-11,-17],[-6,-22],[-2,-26],[2,-32],[6,-46],[-5,-37],[-5,-15],[-35,-28],[-23,-16],[-10,-6],[-15,-1],[-13,4],[-80,69],[-57,54],[-10,16],[-6,13],[-5,12],[-1,12],[-1,17],[5,31],[-1,18],[5,19],[18,35],[19,23],[12,12],[30,22],[26,25],[10,14],[7,16],[7,36],[-2,23],[-6,23],[-9,18],[-35,49],[-21,25],[-39,53],[-46,66],[-72,108],[-19,26],[-20,14]],[[5895,4250],[-14,7],[-18,-1],[-18,-4],[-9,-8],[-24,-67],[-3,-11],[-2,-28],[4,-26],[13,-33],[6,-12],[17,-18],[13,-9],[30,-14],[14,-13],[18,-31],[6,-18],[3,-22],[-1,-34],[-7,-26],[-15,-32],[-8,-11],[-13,-12],[-21,-15],[-18,-8],[-47,-16],[-64,-11],[-68,-14],[-28,-7],[-39,-20],[-21,-13],[-25,-22],[-38,-40],[-72,-99],[-25,-37],[-20,-19],[-9,-6],[-19,-7],[-14,0],[-8,5],[-23,23],[-8,10],[-20,39],[-12,30],[-2,35]],[[5286,3635],[1,21],[5,20],[18,96],[6,48],[-1,25],[-3,14],[-6,12],[-16,20],[-24,23],[-64,47],[-51,52],[-24,-34],[-92,-141],[24,-23],[-65,-103],[14,-34],[6,-29],[-56,-119],[95,-71],[44,-420],[2,-20],[-2,-1],[4,-22],[10,-85],[-40,-35],[-56,-33],[-15,-5],[-4,-2],[-9,2],[-15,4],[-51,27],[42,-259],[2,-27],[-2,-32],[2,-1],[-6,-31],[89,-12],[94,-17],[-1,-6],[-2,-5],[-22,-1],[-12,-10],[12,-16],[10,-18],[2,1],[1,-2],[86,-351],[154,72],[24,21],[62,69],[29,22],[15,8],[18,4],[13,1],[26,-1],[1,-36],[4,-26],[6,-23],[10,-33],[37,-216],[14,-47],[16,-342],[-1,0],[18,-269],[213,6],[-50,-42],[-77,-46],[-22,-17],[-462,-468],[-130,-283],[-12,10],[-44,-133],[131,-68],[11,-16],[26,-27],[-31,-62],[-2,-29],[-7,-19],[-28,-92],[-16,8],[-25,22],[-11,13],[-152,84],[-3,-13],[-51,-6],[-35,-16],[9,87],[-7,1],[-16,33],[-13,13],[-32,23],[-34,9],[-2,-2],[-5,3],[-88,96],[-11,-16],[-9,10],[-1,16],[-5,5],[5,6],[-18,19],[-129,-117],[-25,-14],[-32,-9],[-23,-12],[-14,-5],[-5,5],[8,10],[31,31],[1,5],[-22,18],[-2,5],[1,5],[-6,9],[-7,5],[-8,0],[-4,3],[-12,23],[-8,7],[-11,3],[-20,-4],[-21,2],[-19,4],[-14,-1],[-8,6],[-11,18],[-18,5],[-16,-9],[-30,-21],[-11,-3],[-21,7],[-5,6],[-3,16],[-5,4],[-7,1],[-10,-4],[-9,-6],[-11,-21],[-9,-13],[-2,-8],[-4,-6],[-5,-2],[-6,2],[-7,11],[-4,1],[-3,-2],[-5,-11],[1,-30],[-5,-8],[-8,-3],[-36,18],[-18,2],[-18,26],[-2,2],[-29,36],[-6,20],[9,12],[4,9],[-1,7],[-9,18],[-10,28],[-11,22],[-23,52],[-8,29],[-3,21],[-8,24],[-7,12],[-7,20],[-20,30],[-6,13],[7,27],[6,51],[4,8],[11,13],[20,4],[58,-2],[44,18],[9,9],[7,16],[10,44],[2,16],[-3,50],[2,27],[17,44],[22,46],[25,35],[5,12],[1,9],[-23,66],[-6,29],[-7,11],[-11,5],[-14,2],[-64,17],[-30,4],[-9,6],[-6,8],[-1,8],[9,29],[24,58],[3,28],[7,-2],[-13,42],[-14,29],[-5,18],[-4,24],[-1,32],[-32,-16],[-81,-73],[-12,11],[8,21],[6,24],[2,2],[1,5],[-2,2],[-4,14],[37,131],[5,12],[26,48],[47,-31],[9,11],[4,33],[10,20],[12,-7],[10,-1],[17,5],[17,14],[8,14],[8,24],[4,16],[23,23],[18,25],[8,21],[7,10],[-10,17],[31,29],[-25,38],[4,3],[-8,11],[5,8],[-53,6],[-20,-3],[-34,-10],[-25,-5],[-10,1],[-20,8],[-17,0],[-7,-2],[-7,-8],[-16,-27],[7,-7],[-7,-17],[-12,-18],[-12,-12],[-61,-48],[1,-2],[-10,-7],[-13,26],[-19,-5],[-6,1],[-9,-25],[-106,46],[-52,31],[-15,-29],[-13,20],[-91,64],[-11,20],[-11,13],[-10,6],[-6,11],[-30,23],[-63,10],[-28,14],[-22,9],[-16,1],[-6,3],[-90,14],[-20,18],[-8,14],[-27,39],[-12,12],[-6,12],[-5,-8],[-26,-26],[-45,-59],[-50,-111],[-5,-16],[-6,-27],[-11,-20],[1,-1],[-12,-14],[-15,-10],[-9,-9],[-26,40],[-6,6],[-26,17],[-14,5],[-39,3],[-108,-5],[-4,-5],[-3,-31],[3,-56],[-31,7],[-1,-4],[-14,8],[-26,10],[-24,14],[-15,10],[-24,21],[-24,28],[-16,25],[-10,19],[2,2],[-9,25],[-5,4],[-10,-12],[-9,-22],[-18,-83],[-24,-12],[-14,-4],[-13,-2],[-12,1],[5,-65],[-132,-19],[-6,-5],[-12,-2],[-124,-17],[-16,1],[-15,4],[-28,15],[-15,10],[1,-33],[-33,-22],[37,-73],[56,-88],[13,-26],[20,-59],[8,-39],[5,-52],[-4,-131],[8,-7],[-335,-519],[-215,97],[-104,48],[-377,0],[-147,-40],[-344,33],[-11,-10],[-4,0],[-15,46],[-6,10],[-141,200],[22,23],[-46,66],[31,4],[19,-3],[23,-13],[11,-9],[11,-4],[23,6],[10,-3],[6,2],[10,11],[6,15],[9,14],[11,11],[19,34],[68,88],[-78,25],[9,12],[19,22],[11,7],[64,16],[17,1],[21,-3],[-28,45],[-90,124],[-3,5],[-2,7],[-44,41],[-35,43],[13,14],[-8,11],[-15,9],[4,12],[2,9],[0,33],[0,11],[-6,24],[2,11],[-3,14],[-5,16],[-12,19],[-11,11],[-11,18],[-3,8],[-2,20],[6,58],[8,23],[11,20],[14,19],[14,13],[1,13],[-3,8],[6,31],[1,25],[4,15],[4,9],[5,7],[28,21],[9,10],[8,20],[0,30],[5,14],[5,6],[11,5],[9,-1],[25,-8],[47,4],[12,4],[10,5],[12,14],[10,22],[5,75],[-18,8],[-35,28],[-27,17],[-19,6],[-26,1],[-20,6],[-15,6],[-10,8],[-109,108],[-49,56],[-75,93],[-31,30],[44,69],[13,24],[9,19],[6,26],[6,34],[10,20],[32,53],[2,24],[-7,43],[-10,33],[-17,41],[102,392],[-25,20],[12,3],[9,9],[13,17],[8,14],[2,19],[-2,37],[23,75],[6,9],[11,11],[32,20],[13,11],[9,4],[21,4],[5,36],[21,31],[-2,5],[-9,4],[-1,9],[-3,3],[2,26],[-8,41],[35,27],[4,18],[-2,5],[-4,42],[33,213],[21,-5],[2,16],[-17,98],[-5,15],[-13,-4],[-1,7],[-15,-6],[1,-2],[-18,-6],[-4,-18],[-22,16],[4,10],[-20,17],[7,21],[-33,11],[-11,6],[-66,52],[17,37],[13,74],[-22,12],[-8,7],[-7,10],[-11,31],[-4,6],[-9,8],[-11,6],[-12,2],[-17,0],[-84,-32],[20,110],[-20,101],[-21,96],[-10,42],[0,8],[76,-2],[27,-5],[32,15],[2,-2],[52,-10],[66,-9],[27,-8],[105,-22],[78,-19],[39,-6],[60,169],[32,102],[9,37],[29,63],[118,181],[112,4],[-1,20],[-5,12],[-5,12],[-34,46],[-10,21],[-8,36],[-8,73],[1,18],[-12,102],[-1,13],[2,14],[-5,9],[1,36],[-4,17],[-3,18],[1,18],[4,17],[5,7],[2,9],[-2,8],[-1,18],[-6,19],[-9,104],[21,2],[4,-4],[13,0],[27,-17],[22,57],[-56,59],[-69,51],[-39,36],[-40,32],[-21,23],[-21,17],[-17,17],[-39,43],[-18,12],[-8,0],[-106,106],[-23,34],[-31,28],[-53,61],[-61,53],[-17,21],[-21,29],[-69,70],[-5,3],[-13,2],[-10,7],[-29,29],[-65,55],[-70,73],[-28,23],[-84,52],[-147,64],[-76,38],[13,17],[26,26],[15,26],[14,11],[11,23],[6,5],[10,0],[18,-11],[13,-3],[5,1],[5,12],[3,3],[8,-14],[19,-11],[7,-1],[14,1],[36,-22],[7,-2],[9,1],[6,5],[5,9],[0,5],[-7,19],[-7,10],[-1,9],[-49,23],[20,61],[20,32],[21,-17],[32,-18],[1,1],[9,-4],[9,1],[4,12],[6,12],[-3,14],[1,4],[6,12],[-2,7],[-13,14],[0,2],[7,2],[2,10],[-1,8],[22,19],[-15,41],[-1,8],[25,9],[18,11],[19,16],[17,19],[-34,78],[34,21],[5,0],[4,-3],[2,40],[2,4],[7,3],[-12,35],[45,142],[105,-10],[3,5],[-2,14],[-6,9],[-4,11],[1,36],[-2,9],[-10,22],[-6,8],[-36,29],[4,12],[-29,28],[-19,21],[-25,31],[-28,38],[-288,439],[12,3],[45,13],[37,8],[1,21],[-3,20],[-1,4],[-19,17],[-8,15],[-4,16],[-16,29],[-4,16],[0,7],[-2,9],[2,7],[-1,16],[3,21],[-2,9],[3,8],[-1,6],[3,3],[0,6],[0,3],[4,3],[2,3],[1,3],[1,10],[4,6],[0,8],[1,2],[1,3],[-3,8],[4,6],[0,5],[2,4],[-2,7],[2,7],[-3,6],[3,19],[0,1],[-2,12],[2,9],[-3,8],[0,7],[1,1],[4,8],[2,3],[1,6],[9,12],[0,2],[1,5],[1,4],[4,4],[1,2],[2,10],[9,8],[13,10],[6,1],[3,0],[5,7],[4,1],[1,1],[3,5],[2,0],[7,2],[5,5],[6,6],[1,0],[3,0],[3,1],[5,4],[4,-2],[1,0],[2,2],[6,4],[13,-1],[6,3],[7,4],[2,-2],[1,-2],[8,2],[53,28],[45,20],[2,11],[9,13],[-2,41],[-6,10],[4,20],[-4,4],[4,6],[1,13],[8,15],[1,10],[-5,5],[16,3],[3,-2],[88,-16],[169,-4],[142,10],[6,1],[17,8],[40,8],[27,-17],[23,-4],[16,-17],[4,-1],[13,-11],[7,15],[6,6],[59,14],[28,-11],[9,-2],[13,3],[10,-4],[7,-6],[26,-29],[75,-87],[43,-54],[38,-42],[10,-2],[21,-20],[13,0],[25,-4],[15,-17],[13,-7],[27,1],[12,-3],[18,-12],[-16,-17],[-28,-16],[-14,-11],[-19,-46],[24,-76],[6,-8],[7,-5],[-28,-78],[25,-51],[-56,-127],[24,-85],[-9,-173],[13,-66],[8,10],[10,21],[5,7],[10,6],[11,0],[24,-7],[3,-7],[6,-3],[14,0],[16,-7],[21,-15],[24,-13],[9,-9],[15,-20],[38,-26],[20,-6],[11,-2],[119,1],[27,-8],[33,-15],[25,-19],[36,-36],[36,-57],[-3,-3],[32,-47],[26,-20],[63,-79],[3,-19],[118,65],[144,36],[-10,5],[-3,5],[-9,19],[-2,17],[6,28],[13,46],[31,47],[20,27],[11,12],[7,12],[11,28],[14,33],[14,42],[13,26],[14,16],[18,16],[21,14],[21,5],[41,-8],[64,-2],[15,-1],[7,-2],[10,-6],[6,-6],[16,-22],[18,-32],[8,-9],[11,-7],[14,0],[67,20],[23,5],[16,-5],[19,-14],[29,-14],[21,-5],[12,2],[4,3],[4,4],[4,10],[-3,33],[-3,19],[-5,19],[-13,35],[-4,14],[-4,41],[1,28],[9,19],[7,6],[21,9],[28,5],[41,12],[35,6],[28,19],[30,30],[7,10],[4,12],[3,29],[7,29],[4,10],[6,7],[7,2],[12,1],[35,-9],[28,-2],[6,2],[8,6],[4,4],[4,9],[0,27],[-48,143],[-128,45],[-161,94],[27,70],[6,32],[17,77],[3,114],[14,2],[20,325],[8,150],[4,81],[1,11],[47,-36],[20,-11],[25,-2],[224,-36],[113,-20],[71,8],[13,7],[37,31],[34,18],[9,3],[23,0],[9,1],[11,13],[2,5],[-2,10],[-11,11],[-2,10],[4,7],[5,4],[13,1],[30,8],[17,-2],[22,-14],[29,-12],[25,-14],[17,-15],[20,-12],[28,-32],[4,-3],[11,-4],[9,1],[6,2],[18,24],[21,15],[6,0],[15,-11],[28,-38],[10,-27],[2,-17],[-4,-6],[-6,3],[-7,0],[-4,-2],[-3,-5],[-2,-9],[1,-30],[-4,-3],[-5,-6],[-3,-16],[6,-43],[-11,-28],[-29,-50],[-12,-46],[-3,-24],[0,-12],[2,-9],[22,-49],[9,-28],[-1,-15],[-9,-33],[-1,-11],[1,-8],[9,-28],[1,-18],[84,-25],[76,-64],[10,-20],[-10,-6],[106,-376],[126,79],[20,-70],[131,-123],[8,-15],[-64,-76],[46,-75],[13,0],[57,17],[-3,-57],[27,-53],[-16,-59],[13,-23],[61,-169],[16,-8],[21,12],[136,33],[1,6],[-1,15],[5,6],[104,10],[5,-52],[3,0],[12,-129],[-19,-9],[-22,-5],[-10,-9],[1,-5],[11,2],[7,-2],[10,-8],[5,-9],[32,-123],[4,-24],[1,-51],[2,-11],[24,-56],[-24,-44],[48,-7],[206,-23],[6,3],[4,-11],[59,-12],[-6,43],[298,68],[3,-21],[13,2],[0,6],[2,0],[0,2],[25,5],[10,1],[1,-2],[17,2],[1,0],[4,-8],[9,1],[-2,5],[3,0],[0,-2],[12,2],[2,-14],[7,1],[8,-12],[11,15],[6,-2],[16,4],[4,-4],[5,-1],[8,-15],[19,8],[-5,18],[55,-11],[68,4],[82,20],[62,21],[47,20],[16,-9],[5,-17],[6,3],[25,3],[6,-9],[1,10],[25,17],[6,-1],[6,4],[7,-4],[6,11],[6,-3],[4,9],[-6,5],[4,8],[14,-12],[8,1],[1,5],[7,5],[5,-3],[19,10],[23,-3],[2,0],[10,17],[13,10],[11,4],[16,-3],[4,10],[4,-2],[-1,-4],[11,1],[-1,7],[13,0],[7,3],[0,3],[11,-2],[11,5],[-11,61],[7,2],[1,14],[5,13],[6,10],[4,4],[194,86],[24,14],[19,16],[8,3],[11,11],[11,16],[10,18],[15,35],[16,46],[7,10],[5,-5],[16,-37],[13,-51],[-1,-6],[-2,-5],[-20,-16],[-3,-5],[15,-36],[7,-32],[55,41],[5,-154],[63,-123],[21,-35],[36,-4],[10,-64],[79,2],[6,-6],[45,-25],[30,0],[49,15],[123,63],[36,16],[7,-93],[-57,-24],[89,-415],[-58,-6],[-35,-25],[50,-131],[-250,-98],[3,-3],[18,-14],[81,-79],[62,-82],[54,40],[132,114],[58,-139],[46,45],[5,1],[18,-9],[8,-1],[7,2],[9,7],[14,4],[7,5],[-3,26],[5,17],[5,11],[3,10],[3,64],[5,18],[12,20],[8,5],[25,11],[0,-11],[4,-12],[4,-4],[5,-11],[7,-6],[4,-1],[4,-6],[9,-24],[0,-16],[4,-5],[-2,-10],[5,-9],[7,-3],[4,-10],[4,-26],[-2,-10],[0,-10],[7,-14],[8,-28],[24,-32],[36,16],[35,-6],[44,-1],[24,-17],[57,-42],[274,68],[10,0],[41,-30],[12,3],[60,-10],[-25,141],[6,1],[10,-5],[10,-10],[41,2],[7,3],[4,18],[6,7],[3,1],[0,-3],[10,-1],[7,-4],[4,-6],[9,-4],[8,-1],[9,3],[-3,24],[11,2],[-1,5],[6,19],[-3,10],[-3,1],[-5,13],[-4,35],[-1,44],[2,23],[191,-53],[6,-6],[21,-33],[11,-8],[86,-15],[19,-1],[8,2],[11,4],[32,21],[173,48],[3,-3],[3,-11],[30,-186],[102,41],[165,6],[12,14],[17,-14],[52,4],[-3,-51],[5,-23],[60,-121],[14,13],[22,-15],[77,-54],[31,12],[34,35],[6,2],[159,128],[4,-11],[51,-171],[42,10],[12,-71],[-32,-148],[-21,-79],[26,-208],[0,-17],[-4,-211],[-3,-50],[-9,-88],[0,-14],[1,-12],[14,-38],[29,-48],[10,-24],[16,-48],[4,1],[7,-63],[2,-65],[3,-13],[6,-23],[14,-30],[44,-43],[20,-15],[27,-6],[55,-57],[-57,-41],[-2,-2],[0,-6],[-3,0],[-2,1],[-94,-65],[-12,-8],[-63,-26],[-30,-10],[-8,-9],[-9,-2],[-10,5],[-49,-8],[-12,-1],[-92,-1],[-13,-37],[-13,-41],[-38,-150],[-11,-55],[-2,-21],[1,-23],[5,-23],[13,-32],[18,-27],[37,-37],[58,-55],[23,-24],[-5,-1],[29,-104],[-1,-7],[-12,-27],[49,-20],[41,-23],[37,-30],[25,-24],[16,-19],[32,-44],[28,-53],[20,-54],[13,-51],[-53,-18],[-14,2],[-6,11],[-9,30],[-3,5],[-24,26],[-10,5],[-28,-21],[-12,-2],[-8,-4],[-43,-48],[-10,-8],[-5,2],[-6,7],[-13,26],[-5,6],[-6,2],[-30,0],[-7,5],[-8,13],[-4,29],[-5,7],[-7,1],[-12,-5],[-11,-11],[-23,-12],[-28,2],[-13,-3],[-25,-13],[-19,-13],[-25,-14],[-13,-14],[-15,-25],[-14,-18],[-10,-12],[-9,-5],[-9,0],[-7,4],[-19,24],[-26,14],[-13,2],[-10,-4],[-4,-6],[-1,-7],[3,-12],[-3,-8],[-32,-17],[-36,-37],[-9,-5],[-17,0],[-25,6],[-32,13],[-14,4],[-30,2],[-32,-11],[-10,-7],[-10,-9],[-14,-20],[-3,-8],[-13,-53],[-7,-24],[-24,-43],[-25,-24],[-10,-21],[-3,-15],[2,-7],[7,-5],[30,-4],[47,6],[8,-2],[3,-5],[2,-17],[-2,-17],[2,-13],[0,-15],[-2,-7],[-17,-15],[-12,-2],[-20,6],[-40,23],[-9,3],[-8,-1],[-4,-2],[-54,-37],[-6,-9],[-2,-10],[4,-14],[2,-4],[15,-9],[19,-38],[8,-22],[2,-7],[-1,-16],[-8,-54],[-4,-16],[-11,-26],[-15,-46],[-7,-7],[-13,-6],[-10,-10],[-18,-29],[-6,-16],[-3,-20],[-1,-23],[-4,-13],[12,-28],[-22,-22],[-20,-25],[-21,-39],[-14,-43],[-3,-18],[-2,-48],[2,-25]],[[8821,3378],[-9,-6],[-25,-34],[-30,-48],[-17,-58],[-2,-35],[6,-41]],[[8744,3153],[1,-8],[30,-55],[15,-33],[2,-26],[-6,-15],[-15,-11]],[[8574,3146],[-25,38],[-25,14]],[[8218,3484],[-4,3],[-2,1]],[[7977,3364],[-37,-20]],[[7830,3286],[-6,-3],[-67,-68]],[[7728,3189],[-77,-29]],[[7586,3169],[-6,1],[-20,-2]],[[7536,3164],[-8,-1],[-19,-3],[-1,0]],[[7398,3145],[-2,-1],[-18,-2]],[[7351,3138],[-35,-4],[-43,-14],[-62,-38],[-26,-19]],[[7184,3063],[-64,-45]],[[7098,2996],[-19,-15]],[[6977,2895],[0,-1],[-66,-59]],[[6884,2817],[-32,-5]],[[6843,2814],[-26,9]],[[6795,2841],[-29,46]],[[6757,2911],[-13,76]],[[6739,3013],[-3,20],[-8,50],[-1,44],[-23,55],[-7,22],[-14,52],[-13,34],[-7,90],[0,91],[-1,12]],[[6643,3621],[-1,3],[-2,3]],[[6565,3688],[-8,5],[-68,30],[-8,2]],[[6423,3742],[-7,2],[-7,-5]],[[6284,3572],[-1,-9],[8,-75]],[[6289,3475],[-8,-28]],[[7120,3018],[-22,-22]],[[6228,3406],[-23,-9]],[[6063,3511],[-32,47]],[[6029,3562],[0,53]],[[6030,3636],[22,59]],[[6163,3864],[1,12],[-8,14]],[[6137,3923],[-5,9],[-134,186],[-59,86]],[[5932,4213],[-16,24],[-19,12]],[[5895,4250],[-15,10],[-13,-4]],[[5842,4249],[-2,0],[-1,-3]],[[5833,4235],[-18,-37],[-1,-16]],[[5808,4131],[0,-3],[1,-2]],[[5835,4063],[1,-5],[7,-4]],[[5872,4034],[17,-11],[33,-42]],[[5927,3968],[4,-34]],[[5931,3914],[-10,-37]],[[5908,3851],[-13,-17]],[[5568,3711],[-17,-10],[-30,-37]],[[5514,3655],[-29,-35],[-14,-23]],[[5361,3493],[-5,2]],[[5333,3515],[-18,26]],[[5298,3576],[-12,59]],[[5286,3635],[24,124],[12,63],[-12,59],[-77,64],[-57,49],[-92,104],[-48,24],[-92,-1],[-16,1],[-74,4],[-54,20],[-32,36],[-14,34],[10,58],[21,52],[35,55],[34,58],[5,42],[-18,41],[-27,27],[-35,36],[-50,58],[-54,43],[-31,27],[-56,57]],[[4588,4770],[-180,121],[-192,114],[-190,38],[-173,-14],[-172,10],[-219,63],[-427,209],[-179,189],[-242,132],[-355,220],[-522,57],[-156,64],[-153,122],[-413,333]],[[163,7194],[-161,78]],[[3113,4509],[-122,22],[11,30],[17,14],[17,10],[77,14],[0,-90]],[[3113,5008],[-27,7],[27,27],[0,-34]],[[3076,5124],[-1,-3],[-2,0],[-2,-5],[-1,-2],[-10,5],[2,5],[14,0]],[[2712,4979],[7,21],[17,-8],[-7,-21],[-17,8]],[[2160,4884],[99,-55],[22,64]],[[2281,4893],[34,-6],[6,-4],[2,-7],[-10,-58],[-2,0],[-6,-26],[-3,1]],[[2302,4793],[-57,12],[-8,-38],[60,-14]],[[2297,4753],[0,-2],[-8,-55],[-162,32],[0,67],[33,89]],[[2513,4730],[15,-57],[-45,-18],[-37,54],[67,21]],[[2596,4718],[17,-66],[-48,-20],[-5,0],[-3,4],[-8,27],[-13,53],[-15,60],[1,9],[3,6],[3,5],[6,3],[8,-1],[8,-4],[3,-4],[3,-8],[-1,-16],[-4,-23],[14,-32],[31,7]],[[3018,5066],[-13,-43],[22,-5],[5,-3],[-6,-20],[-12,-4],[-14,0],[-16,2],[-17,4],[-29,13],[-13,10],[-11,26],[3,12],[-4,2],[13,56],[22,-9],[-2,-8],[72,-33]],[[2710,5105],[33,-14],[-22,-76],[-5,2],[-86,36],[-4,2],[18,69],[31,0],[4,-3],[31,-16]],[[2260,5011],[10,-3],[-4,-20],[-10,3],[4,20]],[[2293,5058],[35,-16],[-38,-103],[-8,5],[1,7],[-4,6],[-12,3],[17,82],[7,6],[2,10]],[[3113,4860],[-237,20],[-9,-53],[-23,9],[-12,-36],[-53,23],[13,42],[-6,3],[-28,10],[2,6],[-4,2],[0,7],[-3,0],[1,12],[16,43],[55,-25],[17,70],[-27,11],[14,42],[25,-12],[9,34],[36,-16],[-4,-30],[8,-9],[37,-16],[40,-19],[77,-34],[56,-25],[0,-59]],[[2293,5058],[-41,19],[-3,-19],[-6,3],[-28,15],[5,17],[-14,8],[6,23],[370,0],[-18,-80],[27,-11],[24,-22],[7,29],[3,14],[95,-40],[-19,-40],[41,-16],[-7,-26],[9,-5],[-5,-17],[-15,8],[-4,-10],[-25,8],[-100,3],[-30,-12],[-9,14],[-25,17],[-17,-47],[-5,-37],[-2,-7],[-4,-13],[-38,13],[-3,3],[-111,43],[-7,13],[-26,13],[-5,-14],[-39,21],[6,19],[11,-6],[38,103],[-36,16]],[[2198,5124],[-3,-12],[-7,1],[-36,6],[-11,2],[1,3],[56,0]],[[2166,4972],[-9,3],[4,23],[10,-2],[-5,-24]],[[2710,5105],[-30,19],[35,0],[-5,-19]],[[2237,4767],[8,38],[57,-12],[-5,-40],[-60,14]],[[3113,4707],[-29,-6],[-83,-21],[-24,-6],[-4,-19],[-30,-14],[-50,-19],[-4,-10],[-16,-1],[-19,-1],[-14,-4],[0,-3],[-16,-1],[-4,6],[-3,14],[-21,-4],[-33,-6],[-24,-5],[-1,4],[-10,1],[0,-14],[-8,-2],[-31,9],[-6,3],[-8,-3],[-27,12],[-1,30],[-29,-5],[-5,13],[-16,62],[39,11],[16,5],[38,13],[5,17],[-12,5],[24,76],[-12,6],[11,32],[7,-5],[-1,-4],[13,-8],[2,1],[8,-6],[7,19],[47,-20],[-11,-36],[55,-24],[11,36],[25,-10],[9,54],[28,-3],[94,-9],[88,-11],[25,-2],[0,-147]],[[2920,5124],[-7,-28],[-45,20],[-8,-46],[-9,-34],[-22,11],[-15,-43],[26,-11],[-16,-64],[-42,22],[-42,14],[-4,3],[-4,7],[5,19],[-19,8],[26,90],[-32,14],[6,18],[202,0]],[[2642,5124],[-28,-109],[-22,20],[-26,11],[6,22],[13,56],[57,0]],[[2127,4874],[2,3],[-2,1],[0,246],[82,0],[-7,-22],[15,-9],[-6,-18],[29,-15],[-18,-92],[41,-12],[12,-3],[2,-4],[-9,-25],[-46,6],[-8,-5],[-45,3],[-42,-114],[0,60]],[[2127,4638],[101,-17],[53,-10],[-15,-102],[-65,-25],[-74,-21],[0,175]],[[2626,4456],[-7,19],[21,16],[39,14],[52,3],[9,-1],[3,37],[8,4],[34,6],[74,-14],[-3,-30],[-8,0],[-1,-14],[-16,0],[-1,-39],[17,0],[0,-1],[-221,0]],[[2959,4456],[-1,1],[9,5],[-8,21],[14,6],[7,30],[133,-26],[0,-34],[-16,-3],[-138,0]],[[2863,4492],[37,-6],[-3,-23],[-36,7],[2,22]],[[2514,4828],[1,-1],[0,-1],[0,-1],[0,-1],[0,-1],[0,-1],[-1,-1],[-1,-1],[0,-1],[-1,0],[-1,-1],[-1,0],[-1,0],[-1,0],[-1,0],[-1,0],[0,1],[-1,0],[0,1],[-1,1],[0,1],[-1,1],[0,1],[0,1],[0,1],[1,1],[0,1],[0,1],[1,1],[1,1],[1,1],[1,0],[1,0],[1,0],[1,0],[1,-1],[1,-1],[1,0],[0,-1],[0,-1]],[[2160,4884],[11,31],[110,-22]]]}